pypi_seed/__init__.py
pypi_seed/argsparser.py
pypi_seed/generator.py
pypi_seed/guide.py
pypi_seed/main.py
pypi_seed/project.py
pypi_seed/setting.py
pypi_seed/template_loader.py
pypi_seed/template/__init__.py
pypi_seed/template/cli.setup.py.template
pypi_seed/template/gitignore.py.template
pypi_seed/template/main.py.template
pypi_seed/template/quickstart.en.template
pypi_seed/template/quickstart.sh.template
pypi_seed/template/quickstart.zh.template
pypi_seed/template/readme.md.template
pypi_seed/template/readme.rst.template
pypi_seed/template/setup.py.template
pypi_seed/template/test_main.py.template
tests/__init__.py
tests/argsparser_test.py
tests/generator_test.py
tests/template_loader_test.py
pypi_seed-1.0.9.dist-info/LICENSE
pypi_seed-1.0.9.dist-info/METADATA
pypi_seed-1.0.9.dist-info/WHEEL
pypi_seed-1.0.9.dist-info/entry_points.txt
pypi_seed-1.0.9.dist-info/top_level.txt
pypi_seed-1.0.9.dist-info/RECORD
