Metadata-Version: 2.1
Name: pypi-seed
Version: 1.0.9
Summary: A small tool to demo on upload package to pypi and utility scripts to generate a pypi seed
Home-page: https://github.com/py4ever/pypi_seed
Author: levin
Author-email: 991219092@qq.com
License: Apache License 2.0
Keywords: pypi_seed,seed,generator,levin,leixuewei
Platform: all
Classifier: Development Status :: 5 - Production/Stable
Classifier: Intended Audience :: Developers
Classifier: Operating System :: OS Independent
Classifier: Natural Language :: Chinese (Simplified)
Classifier: Programming Language :: Python
Classifier: Programming Language :: Python :: 2
Classifier: Programming Language :: Python :: 2.7
Classifier: Programming Language :: Python :: 3
Classifier: Programming Language :: Python :: 3.5
Classifier: Programming Language :: Python :: 3.6
Classifier: Programming Language :: Python :: 3.7
Classifier: Programming Language :: Python :: 3.8
Classifier: Programming Language :: Python :: 3.9
Classifier: Topic :: Software Development :: Libraries
License-File: LICENSE
